{
  "raw": {
    "preamble": {
      "bip": "9",
      "title": "Version bits with timeout and delay",
      "author": [
        "Pieter Wuille <pieter.wuille@gmail.com>",
        "Peter Todd <pete@petertodd.org>",
        "Greg Maxwell <greg@xiph.org>",
        "Rusty Russell <rusty@rustcorp.com.au>"
      ],
      "comments_uri": "https://github.com/bitcoin/bips/wiki/Comments:BIP-0009",
      "status": "Final",
      "type": "Informational",
      "created": "2015-10-04",
      "license": [
        "PD"
      ],
      "layer": null,
      "discussions_to": null,
      "comments_summary": "No comments yet.",
      "license_code": null,
      "post_history": null,
      "requires": null,
      "replaces": null,
      "superseded_by": null
    }
  },
  "metadata": {
    "last_commit": "Wed Jun 9 10:33:59 2021 +1000",
    "total_commits": 44,
    "git_history": [
      [
        "f59b209b913b2b45c99436ac3bce7cd86d623000",
        "Wed Jun 9 10:33:59 2021 +1000",
        "Tobin Harding"
      ],
      [
        "9ee97173106dfb0886e335a00df1359f6d4279c7",
        "Wed Jun 9 10:15:53 2021 +1000",
        "Tobin Harding"
      ],
      [
        "593324754f0494070bb4a6a472e02080af5c3c0e",
        "Wed Apr 14 08:53:21 2021 -1000",
        "fresheneesz"
      ],
      [
        "cda85c75c176ebeba4152a238998b4c54aa74e89",
        "Mon Apr 12 08:26:18 2021 -1000",
        "fresheneesz"
      ],
      [
        "0c3af69468f9ebdbf080d5c1b76ed4289b28f8eb",
        "Wed Sep 2 15:57:56 2020 -0500",
        "Josh Klopfenstein"
      ],
      [
        "6295c1a095a1fa33f38d334227fa4222d8e0a523",
        "Thu Aug 24 23:50:20 2017 +1200",
        "MeshCollider"
      ],
      [
        "959fecc15bdad070afa63455468b1dba54655fa6",
        "Wed Nov 30 09:47:31 2016 +0000",
        "Luke Dashjr"
      ],
      [
        "d35a3d33da628fb3da543bb8652a2153d65562c5",
        "Sat Aug 20 23:50:14 2016 +0000",
        "Luke Dashjr"
      ],
      [
        "5e6dc77d6bfd53b7a6c2d350c9f7d59d70f0d85a",
        "Mon Jun 20 01:47:03 2016 +0800",
        "Johnson Lau"
      ],
      [
        "3dc43c84b134b4318376f40015a6840f6d900d14",
        "Wed Jun 1 17:54:45 2016 +0100",
        "Chris Wheeler"
      ],
      [
        "55ecc6fd38c8e90100463fb4df767be8896f716b",
        "Tue May 31 18:08:56 2016 +0000",
        "Luke-Jr"
      ],
      [
        "a95b8f8796533f52061d62442d8a596ba65902fc",
        "Wed May 11 21:54:09 2016 +0000",
        "Luke Dashjr"
      ],
      [
        "949bb13c1d1d4f5b1d1166c6ff33c924dae47dc3",
        "Wed May 11 17:45:08 2016 +0000",
        "Luke Dashjr"
      ],
      [
        "d28a720f2aed00c2051b51402d4093062a8c431a",
        "Mon Apr 25 00:18:39 2016 +0000",
        "Luke Dashjr"
      ],
      [
        "074909a173cc5c425f057dba12dad8bf52eb0eab",
        "Sat Apr 23 21:13:02 2016 +0000",
        "Luke Dashjr"
      ],
      [
        "baacb0c64572548829db9a0609036b17e5d25a5c",
        "Sat Apr 23 20:32:59 2016 +0000",
        "Luke Dashjr"
      ],
      [
        "adbf64c626ca4e79bd4ff983ec37d9ffd8577148",
        "Sat Apr 23 20:20:13 2016 +0000",
        "Luke Dashjr"
      ],
      [
        "c7a31304e7741aa369864059ea183ae8e3b0aa33",
        "Sat Apr 23 20:12:41 2016 +0000",
        "Luke Dashjr"
      ],
      [
        "4c124a8c5dad794b9c13d27990fa42651f44676f",
        "Wed Mar 30 22:38:57 2016 +0000",
        "Luke Dashjr"
      ],
      [
        "4e9591d8c787f0d32b5a79862c8570300dc742d6",
        "Wed Mar 30 22:22:09 2016 +0000",
        "Luke Dashjr"
      ],
      [
        "b8907db95076abe39596934d4f04a3b8ffce0160",
        "Wed Mar 30 21:58:51 2016 +0000",
        "Luke Dashjr"
      ],
      [
        "580db159079a7a8f0ee3d6646e7e6a668fce00a2",
        "Tue May 17 02:06:18 2016 +0200",
        "Steven Roose"
      ],
      [
        "1a3613622b15cb85c301e3ab29697b8c19804421",
        "Sat May 14 14:22:56 2016 +0200",
        "Steven Roose"
      ],
      [
        "f71727f1c38ab42b7c28b50aa491b3243e04cbfd",
        "Sat May 14 14:21:46 2016 +0200",
        "Steven Roose"
      ],
      [
        "b56f7d7b6da75a31acfff42a678ed31b0555259f",
        "Sat May 7 07:17:02 2016 +0100",
        "BtcDrak"
      ],
      [
        "bce835d2ce0172bffa2858eaba21a6c6c3723110",
        "Tue Mar 15 16:29:24 2016 +0100",
        "Pieter Wuille"
      ],
      [
        "4c4009bfdb94d10d94908a144d768399cf40ea6f",
        "Thu Mar 10 13:18:03 2016 +1030",
        "Rusty Russell"
      ],
      [
        "7314d13a08a72ded7d6cdaa32d1b4b88d8b76832",
        "Thu Mar 10 13:27:09 2016 +1030",
        "Rusty Russell"
      ],
      [
        "c6f8e3ae62dcf8fa9f464928f3d71d4cae4d6022",
        "Mon Mar 7 16:51:59 2016 +0100",
        "Jonathan Cross"
      ],
      [
        "a3df16e6504769498c51af88afd4cf2148896bd0",
        "Wed Mar 2 19:59:18 2016 +0100",
        "Pieter Wuille"
      ],
      [
        "cd6dfb94116224d552b3cc884b3454deeeaf0ad8",
        "Wed Mar 2 19:48:34 2016 +0100",
        "Pieter Wuille"
      ],
      [
        "63d626668c01c6aaa5baadf7f80341d6eed0b090",
        "Wed Mar 2 19:42:41 2016 +0100",
        "Pieter Wuille"
      ],
      [
        "760e2a15bf04f888ee6c40f90d70ceac25c315c4",
        "Wed Mar 2 19:19:42 2016 +0100",
        "Pieter Wuille"
      ],
      [
        "a4493063735f2e221f7a2c8d032bb172c8498147",
        "Wed Mar 2 05:37:51 2016 +0100",
        "Pieter Wuille"
      ],
      [
        "8315dfd3faf8c2af74ac6185269fcebc89d41c26",
        "Tue Mar 1 04:05:48 2016 +0100",
        "Pieter Wuille"
      ],
      [
        "737bf29de2338d6f612533bbb9860a85169a3c33",
        "Tue Mar 1 01:24:34 2016 +0100",
        "Pieter Wuille"
      ],
      [
        "226bd097a9d5e03a9cdb1b3b00c79cd017c8983a",
        "Tue Mar 1 01:06:16 2016 +0100",
        "Pieter Wuille"
      ],
      [
        "2b27bb5d27586f6f17f5c61cf8b7a6ad5a4588f6",
        "Tue Mar 1 00:25:30 2016 +0000",
        "Luke-Jr"
      ],
      [
        "4edd6d2badd9a6ad2ff09bb6792fe0d0e365a7de",
        "Wed Feb 3 07:02:36 2016 +0000",
        "Luke Dashjr"
      ],
      [
        "94820a96b5cefc06c1bb05493a111c47faf778b9",
        "Sat Nov 28 16:32:08 2015 -0500",
        "Eric Lombrozo"
      ],
      [
        "64fda4ea054314a188899cfc6aef25ddd1ad3676",
        "Tue Nov 17 06:02:55 2015 -0500",
        "Eric Lombrozo"
      ],
      [
        "fd189fdccd7e3c3caef01313df9c36f621af6d04",
        "Fri Oct 2 10:50:18 2015 +0930",
        "Rusty Russell"
      ],
      [
        "602e72125637ed90b75009e10fb5ba8a9cab3198",
        "Sun Sep 27 15:22:45 2015 +0930",
        "Rusty Russell"
      ],
      [
        "f278c02cbcc18b20d7eb1c68653e4368f3852f5c",
        "Fri Sep 25 12:16:11 2015 +0930",
        "Rusty Russell"
      ]
    ],
    "contributors": 14
  },
  "compliance": {
    "score": 89.66,
    "passed_checks": 26,
    "failed_checks": 3,
    "skipped_checks": 12,
    "total_checks": 29,
    "bip2": {
      "score": 100.0,
      "passed_checks": 12,
      "failed_checks": 0,
      "skipped_checks": 0,
      "total_checks": 12,
      "checks": [
        {
          "id": "bip2.required_field.bip",
          "label": "Required field 'bip' is present",
          "category": "required_field",
          "standard": "bip2",
          "passed": true,
          "details": null
        },
        {
          "id": "bip2.required_field.title",
          "label": "Required field 'title' is present",
          "category": "required_field",
          "standard": "bip2",
          "passed": true,
          "details": null
        },
        {
          "id": "bip2.required_field.author",
          "label": "Required field 'author' is present",
          "category": "required_field",
          "standard": "bip2",
          "passed": true,
          "details": null
        },
        {
          "id": "bip2.required_field.comments_uri",
          "label": "Required field 'comments_uri' is present",
          "category": "required_field",
          "standard": "bip2",
          "passed": true,
          "details": null
        },
        {
          "id": "bip2.required_field.status",
          "label": "Required field 'status' is present",
          "category": "required_field",
          "standard": "bip2",
          "passed": true,
          "details": null
        },
        {
          "id": "bip2.required_field.type",
          "label": "Required field 'type' is present",
          "category": "required_field",
          "standard": "bip2",
          "passed": true,
          "details": null
        },
        {
          "id": "bip2.required_field.created",
          "label": "Required field 'created' is present",
          "category": "required_field",
          "standard": "bip2",
          "passed": true,
          "details": null
        },
        {
          "id": "bip2.required_field.license",
          "label": "Required field 'license' is present",
          "category": "required_field",
          "standard": "bip2",
          "passed": true,
          "details": null
        },
        {
          "id": "bip2.heading.abstract",
          "label": "Heading 'abstract' exists at level 2",
          "category": "heading",
          "standard": "bip2",
          "passed": true,
          "details": null
        },
        {
          "id": "bip2.heading.motivation",
          "label": "Heading 'motivation' exists at level 2",
          "category": "heading",
          "standard": "bip2",
          "passed": true,
          "details": null
        },
        {
          "id": "bip2.heading.specification",
          "label": "Heading 'specification' exists at level 2",
          "category": "heading",
          "standard": "bip2",
          "passed": true,
          "details": null
        },
        {
          "id": "bip2.heading.copyright",
          "label": "Heading 'copyright' exists at level 2",
          "category": "heading",
          "standard": "bip2",
          "passed": true,
          "details": null
        }
      ]
    },
    "bip3": {
      "score": 82.35,
      "passed_checks": 14,
      "failed_checks": 3,
      "skipped_checks": 12,
      "total_checks": 17,
      "checks": [
        {
          "id": "bip3.preamble.top_rfc822",
          "label": "Preamble exists as RFC-822-style metadata at the top",
          "category": "preamble",
          "standard": "bip3",
          "passed": true,
          "details": null
        },
        {
          "id": "bip3.required_header.bip",
          "label": "Required header 'bip' is present",
          "category": "required_header",
          "standard": "bip3",
          "passed": true,
          "details": null
        },
        {
          "id": "bip3.required_header.title",
          "label": "Required header 'title' is present",
          "category": "required_header",
          "standard": "bip3",
          "passed": true,
          "details": null
        },
        {
          "id": "bip3.required_header.authors",
          "label": "Required header 'authors' is present",
          "category": "required_header",
          "standard": "bip3",
          "passed": false,
          "details": "Missing required header 'authors'"
        },
        {
          "id": "bip3.required_header.status",
          "label": "Required header 'status' is present",
          "category": "required_header",
          "standard": "bip3",
          "passed": true,
          "details": null
        },
        {
          "id": "bip3.required_header.type",
          "label": "Required header 'type' is present",
          "category": "required_header",
          "standard": "bip3",
          "passed": true,
          "details": null
        },
        {
          "id": "bip3.required_header.assigned",
          "label": "Required header 'assigned' is present",
          "category": "required_header",
          "standard": "bip3",
          "passed": false,
          "details": "Missing required header 'assigned'"
        },
        {
          "id": "bip3.required_header.license",
          "label": "Required header 'license' is present",
          "category": "required_header",
          "standard": "bip3",
          "passed": true,
          "details": null
        },
        {
          "id": "bip3.header_order",
          "label": "Headers appear in the expected BIP3 order",
          "category": "header_order",
          "standard": "bip3",
          "passed": true,
          "details": null
        },
        {
          "id": "bip3.header_value.bip",
          "label": "Header 'BIP' is an integer without leading zeros or '?'",
          "category": "header_value",
          "standard": "bip3",
          "passed": true,
          "details": null
        },
        {
          "id": "bip3.header_value.title",
          "label": "Header 'Title' is 50 characters or fewer",
          "category": "header_value",
          "standard": "bip3",
          "passed": true,
          "details": null
        },
        {
          "id": "bip3.header_value.authors",
          "label": "Header 'authors' uses 'Name <email>' entries",
          "category": "header_value",
          "standard": "bip3",
          "passed": null,
          "details": null
        },
        {
          "id": "bip3.header_value.deputies",
          "label": "Header 'deputies' uses 'Name <email>' entries",
          "category": "header_value",
          "standard": "bip3",
          "passed": null,
          "details": null
        },
        {
          "id": "bip3.header_value.status",
          "label": "Header 'Status' is one of Draft, Complete, Deployed, Closed",
          "category": "header_value",
          "standard": "bip3",
          "passed": false,
          "details": "Invalid Status 'Final'"
        },
        {
          "id": "bip3.header_value.type",
          "label": "Header 'Type' is one of Specification, Informational, Process",
          "category": "header_value",
          "standard": "bip3",
          "passed": true,
          "details": null
        },
        {
          "id": "bip3.header_value.assigned",
          "label": "Header 'Assigned' is yyyy-mm-dd or '?'",
          "category": "header_value",
          "standard": "bip3",
          "passed": null,
          "details": null
        },
        {
          "id": "bip3.header_value.license",
          "label": "Header 'License' is non-empty",
          "category": "header_value",
          "standard": "bip3",
          "passed": true,
          "details": null
        },
        {
          "id": "bip3.header_value.discussion",
          "label": "Header 'Discussion' uses 'yyyy-mm-dd: URL' lines",
          "category": "header_value",
          "standard": "bip3",
          "passed": null,
          "details": null
        },
        {
          "id": "bip3.header_value.version",
          "label": "Header 'Version' uses MAJOR.MINOR.PATCH",
          "category": "header_value",
          "standard": "bip3",
          "passed": null,
          "details": null
        },
        {
          "id": "bip3.header_value.requires",
          "label": "Header 'requires' uses comma+space separated BIP numbers",
          "category": "header_value",
          "standard": "bip3",
          "passed": null,
          "details": null
        },
        {
          "id": "bip3.header_value.replaces",
          "label": "Header 'replaces' uses comma+space separated BIP numbers",
          "category": "header_value",
          "standard": "bip3",
          "passed": null,
          "details": null
        },
        {
          "id": "bip3.header_value.proposed_replacement",
          "label": "Header 'proposed_replacement' uses comma+space separated BIP numbers",
          "category": "header_value",
          "standard": "bip3",
          "passed": null,
          "details": null
        },
        {
          "id": "bip3.required_section.abstract",
          "label": "Required section 'abstract' is present",
          "category": "required_section",
          "standard": "bip3",
          "passed": true,
          "details": null
        },
        {
          "id": "bip3.required_section.motivation",
          "label": "Required section 'motivation' is present",
          "category": "required_section",
          "standard": "bip3",
          "passed": true,
          "details": null
        },
        {
          "id": "bip3.required_section.copyright",
          "label": "Required section 'copyright' is present",
          "category": "required_section",
          "standard": "bip3",
          "passed": true,
          "details": null
        },
        {
          "id": "bip3.type_specific.specification_section",
          "label": "Type 'Specification' includes a 'Specification' section",
          "category": "type_specific",
          "standard": "bip3",
          "passed": null,
          "details": null
        },
        {
          "id": "bip3.changelog.changelog_section",
          "label": "Complete/Deployed proposals include a 'Changelog' section",
          "category": "changelog",
          "standard": "bip3",
          "passed": null,
          "details": null
        },
        {
          "id": "bip3.changelog.version_header",
          "label": "Complete/Deployed proposals include a 'Version' header",
          "category": "changelog",
          "standard": "bip3",
          "passed": null,
          "details": null
        },
        {
          "id": "bip3.changelog.version_matches",
          "label": "Latest changelog version matches the 'Version' header",
          "category": "changelog",
          "standard": "bip3",
          "passed": null,
          "details": null
        }
      ]
    }
  },
  "insights": {
    "word_list": {
      "block": 34,
      "bit": 28,
      "bip": 27,
      "soft": 23,
      "state": 21,
      "nversion": 16,
      "fork": 15,
      "deployment": 15,
      "bits": 13,
      "period": 12,
      "mediawiki": 12,
      "set": 12,
      "version": 11,
      "timeout": 11,
      "failed": 11,
      "return": 11,
      "blocks": 10,
      "locked_in": 10,
      "active": 10,
      "retarget": 9,
      "height": 9,
      "deployments": 9,
      "2016": 9,
      "0": 8,
      "1": 8,
      "s": 8,
      "started": 8,
      "template": 8,
      "changes": 7,
      "forks": 7,
      "use": 7,
      "software": 7,
      "rules": 7,
      "parent": 7,
      "softfork": 7,
      "change": 6,
      "consensus": 6,
      "number": 6,
      "threshold": 6,
      "starttime": 6,
      "time": 6,
      "past": 6,
      "possible": 6,
      "defined": 6,
      "field": 5,
      "34": 5,
      "mechanism": 5,
      "support": 5,
      "future": 5,
      "integer": 5,
      "2": 5,
      "rule": 5,
      "values": 5,
      "upgrade": 5,
      "states": 5,
      "new": 5,
      "getmediantimepast": 5,
      "case": 5,
      "walk": 5,
      "warning": 5,
      "key": 5,
      "comments": 4,
      "specifies": 4,
      "numbers": 4,
      "valid": 4,
      "allows": 4,
      "system": 4,
      "pre": 3,
      "com": 3,
      "0009": 3,
      "type": 3,
      "later": 3,
      "proposals": 3,
      "long": 3,
      "95": 3,
      "reached": 3,
      "66": 3,
      "65": 3,
      "3": 3,
      "chain": 3,
      "description": 3,
      "n": 3,
      "median": 3,
      "including": 3,
      "selected": 3,
      "release": 3,
      "001": 3,
      "0x20000000": 3,
      "treated": 3,
      "transitions": 3,
      "getstateforblock": 3,
      "transition": 3,
      "non": 3,
      "count": 3,
      "unknown": 3,
      "mask": 3,
      "object": 3,
      "list": 3,
      "vbavailable": 3,
      "prefix": 3,
      "attempt": 3,
      "account": 3,
      "conflicting": 3,
      "pieter": 2,
      "wuille": 2,
      "org": 2,
      "greg": 2,
      "rusty": 2,
      "bitcoin": 2,
      "bips": 2,
      "10": 2,
      "document": 2,
      "proposed": 2,
      "allowing": 2,
      "multiple": 2,
      "compatible": 2,
      "relies": 2,
      "interpreting": 2,
      "independent": 2,
      "fallow": 2,
      "pause": 2,
      "reused": 2,
      "0034": 2,
      "flag": 2,
      "integers": 2,
      "supports": 2,
      "single": 2,
      "rolled": 2,
      "sup": 2,
      "interpreted": 2,
      "indicates": 2,
      "approach": 2,
      "permanently": 2,
      "restricts": 2,
      "0066": 2,
      "0065": 2,
      "following": 2,
      "parameters": 2,
      "reasonable": 2,
      "described": 2,
      "recommended": 2,
      "lock": 2,
      "activation": 2,
      "considered": 2,
      "locked": 2,
      "guidelines": 2,
      "softforks": 2,
      "concurrent": 2,
      "date": 2,
      "delays": 2,
      "previous": 2,
      "buggy": 2,
      "genesis": 2,
      "definition": 2,
      "range": 2,
      "0x3fffffff": 2,
      "purposes": 2,
      "upgrades": 2,
      "miners": 2,
      "setting": 2,
      "effect": 2,
      "img": 2,
      "floor": 2,
      "guaranteed": 2,
      "depends": 2,
      "switch": 2,
      "refers": 2,
      "1916": 2,
      "demand": 2,
      "maintained": 2,
      "combination": 2,
      "warnings": 2,
      "zero": 2,
      "warn": 2,
      "loudly": 2,
      "request": 2,
      "extended": 2,
      "class": 2,
      "wikitable": 2,
      "colspan": 2,
      "4": 2,
      "required": 2,
      "array": 2,
      "strings": 2,
      "supported": 2,
      "yes": 2,
      "vbrequired": 2,
      "server": 2,
      "enabled": 2,
      "versionbits": 2,
      "clear": 2,
      "listed": 2,
      "prefixed": 2,
      "clients": 2,
      "examples": 2,
      "client": 2,
      "understand": 2,
      "unmodified": 2,
      "mining": 2,
      "generation": 2,
      "transaction": 2,
      "modifies": 2,
      "point": 2
    },
    "explicit_references": [
      "BIP 34",
      "BIP 65",
      "BIP 66"
    ],
    "explicit_dependencies": [],
    "implicit_dependencies": [
      "BIP 34",
      "BIP 65",
      "BIP 66"
    ]
  }
}
