{
  "raw": {
    "preamble": {
      "bip": "159",
      "title": "NODE_NETWORK_LIMITED service bit",
      "author": [
        "Jonas Schnelli <dev@jonasschnelli.ch>"
      ],
      "comments_uri": "https://github.com/bitcoin/bips/wiki/Comments:BIP-0159",
      "status": "Draft",
      "type": "Standards Track",
      "created": "2017-05-11",
      "license": [
        "BSD-2-Clause"
      ],
      "layer": "Peer Services",
      "discussions_to": null,
      "comments_summary": "No comments yet.",
      "license_code": null,
      "post_history": null,
      "requires": null,
      "replaces": null,
      "superseded_by": null
    }
  },
  "metadata": {
    "last_commit": "Sun Oct 28 07:01:19 2018 +0330",
    "total_commits": 8,
    "metadata_last_updated": "2026-03-18T16:12:53",
    "git_history": [
      [
        "6c99f7a3efa86b995fa73156cf2af73b497d5c3a",
        "Sun Oct 28 07:01:19 2018 +0330",
        "Coding Enthusiast"
      ],
      [
        "fa9a4f307eb241b69f04681c3da35b7f69cf9fd5",
        "Tue Dec 19 14:01:35 2017 -0500",
        "MarcoFalke"
      ],
      [
        "fa810b3bff542200c50c4fd33fcfd982142b63ed",
        "Tue Dec 19 13:52:46 2017 -0500",
        "MarcoFalke"
      ],
      [
        "8b971ea4deb5c99bbf99914b84d687982000ba22",
        "Sat Sep 23 09:23:38 2017 -0600",
        "Jonas Schnelli"
      ],
      [
        "ee45bbc7c4962d4b551d730469749bb35df18757",
        "Fri Aug 11 21:25:14 2017 +0200",
        "Jonas Schnelli"
      ],
      [
        "f1e884b75acb577a2aecb3f29323c767595efaf8",
        "Tue Aug 8 22:20:37 2017 +0200",
        "Jonas Schnelli"
      ],
      [
        "677e6e31efdc0d2ede7a0f6d2c2ae4fee0a60416",
        "Tue Aug 8 10:38:54 2017 +0200",
        "Jonas Schnelli"
      ],
      [
        "ec403b0ac53bbf248493da219a191df494795a4a",
        "Mon Aug 7 19:29:04 2017 +0200",
        "Jonas Schnelli"
      ]
    ],
    "contributors": 3
  },
  "compliance": {
    "score": 79.41,
    "passed_checks": 27,
    "failed_checks": 7,
    "skipped_checks": 12,
    "total_checks": 34,
    "bip2": {
      "score": 76.47,
      "passed_checks": 13,
      "failed_checks": 4,
      "skipped_checks": 0,
      "total_checks": 17,
      "checks": [
        {
          "id": "bip2.required_field.bip",
          "label": "Required field 'bip' is present",
          "category": "required_field",
          "standard": "bip2",
          "passed": true,
          "details": null
        },
        {
          "id": "bip2.required_field.title",
          "label": "Required field 'title' is present",
          "category": "required_field",
          "standard": "bip2",
          "passed": true,
          "details": null
        },
        {
          "id": "bip2.required_field.author",
          "label": "Required field 'author' is present",
          "category": "required_field",
          "standard": "bip2",
          "passed": true,
          "details": null
        },
        {
          "id": "bip2.required_field.comments_uri",
          "label": "Required field 'comments_uri' is present",
          "category": "required_field",
          "standard": "bip2",
          "passed": true,
          "details": null
        },
        {
          "id": "bip2.required_field.status",
          "label": "Required field 'status' is present",
          "category": "required_field",
          "standard": "bip2",
          "passed": true,
          "details": null
        },
        {
          "id": "bip2.required_field.type",
          "label": "Required field 'type' is present",
          "category": "required_field",
          "standard": "bip2",
          "passed": true,
          "details": null
        },
        {
          "id": "bip2.required_field.created",
          "label": "Required field 'created' is present",
          "category": "required_field",
          "standard": "bip2",
          "passed": true,
          "details": null
        },
        {
          "id": "bip2.required_field.license",
          "label": "Required field 'license' is present",
          "category": "required_field",
          "standard": "bip2",
          "passed": true,
          "details": null
        },
        {
          "id": "bip2.heading.abstract",
          "label": "Heading 'abstract' exists at level 2",
          "category": "heading",
          "standard": "bip2",
          "passed": true,
          "details": null
        },
        {
          "id": "bip2.heading.motivation",
          "label": "Heading 'motivation' exists at level 2",
          "category": "heading",
          "standard": "bip2",
          "passed": true,
          "details": null
        },
        {
          "id": "bip2.heading.specification",
          "label": "Heading 'specification' exists at level 2",
          "category": "heading",
          "standard": "bip2",
          "passed": true,
          "details": null
        },
        {
          "id": "bip2.heading.rationale",
          "label": "Heading 'rationale' exists at level 2",
          "category": "heading",
          "standard": "bip2",
          "passed": false,
          "details": "Missing heading 'rationale'"
        },
        {
          "id": "bip2.heading.backwards_compatibility",
          "label": "Heading 'backwards compatibility' exists at level 2",
          "category": "heading",
          "standard": "bip2",
          "passed": false,
          "details": "Missing heading 'backwards compatibility'"
        },
        {
          "id": "bip2.heading.reference_implementation",
          "label": "Heading 'reference implementation' exists at level 2",
          "category": "heading",
          "standard": "bip2",
          "passed": true,
          "details": null
        },
        {
          "id": "bip2.heading.security_considerations",
          "label": "Heading 'security considerations' exists at level 2",
          "category": "heading",
          "standard": "bip2",
          "passed": false,
          "details": "Missing heading 'security considerations'"
        },
        {
          "id": "bip2.heading.copyright",
          "label": "Heading 'copyright' exists at level 2",
          "category": "heading",
          "standard": "bip2",
          "passed": true,
          "details": null
        },
        {
          "id": "bip2.heading.references",
          "label": "Heading 'references' exists at level 2",
          "category": "heading",
          "standard": "bip2",
          "passed": false,
          "details": "Missing heading 'references'"
        }
      ]
    },
    "bip3": {
      "score": 82.35,
      "passed_checks": 14,
      "failed_checks": 3,
      "skipped_checks": 12,
      "total_checks": 17,
      "checks": [
        {
          "id": "bip3.preamble.top_rfc822",
          "label": "Preamble exists as RFC-822-style metadata at the top",
          "category": "preamble",
          "standard": "bip3",
          "passed": true,
          "details": null
        },
        {
          "id": "bip3.required_header.bip",
          "label": "Required header 'bip' is present",
          "category": "required_header",
          "standard": "bip3",
          "passed": true,
          "details": null
        },
        {
          "id": "bip3.required_header.title",
          "label": "Required header 'title' is present",
          "category": "required_header",
          "standard": "bip3",
          "passed": true,
          "details": null
        },
        {
          "id": "bip3.required_header.authors",
          "label": "Required header 'authors' is present",
          "category": "required_header",
          "standard": "bip3",
          "passed": false,
          "details": "Missing required header 'authors'"
        },
        {
          "id": "bip3.required_header.status",
          "label": "Required header 'status' is present",
          "category": "required_header",
          "standard": "bip3",
          "passed": true,
          "details": null
        },
        {
          "id": "bip3.required_header.type",
          "label": "Required header 'type' is present",
          "category": "required_header",
          "standard": "bip3",
          "passed": true,
          "details": null
        },
        {
          "id": "bip3.required_header.assigned",
          "label": "Required header 'assigned' is present",
          "category": "required_header",
          "standard": "bip3",
          "passed": false,
          "details": "Missing required header 'assigned'"
        },
        {
          "id": "bip3.required_header.license",
          "label": "Required header 'license' is present",
          "category": "required_header",
          "standard": "bip3",
          "passed": true,
          "details": null
        },
        {
          "id": "bip3.header_order",
          "label": "Headers appear in the expected BIP3 order",
          "category": "header_order",
          "standard": "bip3",
          "passed": true,
          "details": null
        },
        {
          "id": "bip3.header_value.bip",
          "label": "Header 'BIP' is an integer without leading zeros or '?'",
          "category": "header_value",
          "standard": "bip3",
          "passed": true,
          "details": null
        },
        {
          "id": "bip3.header_value.title",
          "label": "Header 'Title' is 50 characters or fewer",
          "category": "header_value",
          "standard": "bip3",
          "passed": true,
          "details": null
        },
        {
          "id": "bip3.header_value.authors",
          "label": "Header 'authors' uses 'Name <email>' entries",
          "category": "header_value",
          "standard": "bip3",
          "passed": null,
          "details": null
        },
        {
          "id": "bip3.header_value.deputies",
          "label": "Header 'deputies' uses 'Name <email>' entries",
          "category": "header_value",
          "standard": "bip3",
          "passed": null,
          "details": null
        },
        {
          "id": "bip3.header_value.status",
          "label": "Header 'Status' is one of Draft, Complete, Deployed, Closed",
          "category": "header_value",
          "standard": "bip3",
          "passed": true,
          "details": null
        },
        {
          "id": "bip3.header_value.type",
          "label": "Header 'Type' is one of Specification, Informational, Process",
          "category": "header_value",
          "standard": "bip3",
          "passed": false,
          "details": "Invalid Type 'Standards Track'"
        },
        {
          "id": "bip3.header_value.assigned",
          "label": "Header 'Assigned' is yyyy-mm-dd or '?'",
          "category": "header_value",
          "standard": "bip3",
          "passed": null,
          "details": null
        },
        {
          "id": "bip3.header_value.license",
          "label": "Header 'License' is non-empty",
          "category": "header_value",
          "standard": "bip3",
          "passed": true,
          "details": null
        },
        {
          "id": "bip3.header_value.discussion",
          "label": "Header 'Discussion' uses 'yyyy-mm-dd: URL' lines",
          "category": "header_value",
          "standard": "bip3",
          "passed": null,
          "details": null
        },
        {
          "id": "bip3.header_value.version",
          "label": "Header 'Version' uses MAJOR.MINOR.PATCH",
          "category": "header_value",
          "standard": "bip3",
          "passed": null,
          "details": null
        },
        {
          "id": "bip3.header_value.requires",
          "label": "Header 'requires' uses comma+space separated BIP numbers",
          "category": "header_value",
          "standard": "bip3",
          "passed": null,
          "details": null
        },
        {
          "id": "bip3.header_value.replaces",
          "label": "Header 'replaces' uses comma+space separated BIP numbers",
          "category": "header_value",
          "standard": "bip3",
          "passed": null,
          "details": null
        },
        {
          "id": "bip3.header_value.proposed_replacement",
          "label": "Header 'proposed_replacement' uses comma+space separated BIP numbers",
          "category": "header_value",
          "standard": "bip3",
          "passed": null,
          "details": null
        },
        {
          "id": "bip3.required_section.abstract",
          "label": "Required section 'abstract' is present",
          "category": "required_section",
          "standard": "bip3",
          "passed": true,
          "details": null
        },
        {
          "id": "bip3.required_section.motivation",
          "label": "Required section 'motivation' is present",
          "category": "required_section",
          "standard": "bip3",
          "passed": true,
          "details": null
        },
        {
          "id": "bip3.required_section.copyright",
          "label": "Required section 'copyright' is present",
          "category": "required_section",
          "standard": "bip3",
          "passed": true,
          "details": null
        },
        {
          "id": "bip3.type_specific.specification_section",
          "label": "Type 'Specification' includes a 'Specification' section",
          "category": "type_specific",
          "standard": "bip3",
          "passed": null,
          "details": null
        },
        {
          "id": "bip3.changelog.changelog_section",
          "label": "Complete/Deployed proposals include a 'Changelog' section",
          "category": "changelog",
          "standard": "bip3",
          "passed": null,
          "details": null
        },
        {
          "id": "bip3.changelog.version_header",
          "label": "Complete/Deployed proposals include a 'Version' header",
          "category": "changelog",
          "standard": "bip3",
          "passed": null,
          "details": null
        },
        {
          "id": "bip3.changelog.version_matches",
          "label": "Latest changelog version matches the 'Version' header",
          "category": "changelog",
          "standard": "bip3",
          "passed": null,
          "details": null
        }
      ]
    }
  },
  "insights": {
    "word_list": {
      "peers": 14,
      "code": 14,
      "blocks": 10,
      "service": 9,
      "peer": 8,
      "pruned": 8,
      "node_network_limited": 7,
      "bit": 7,
      "bip": 6,
      "bitcoin": 6,
      "services": 4,
      "comments": 4,
      "relay": 4,
      "signaling": 4,
      "depth": 4,
      "https": 3,
      "github": 3,
      "com": 3,
      "2": 3,
      "historical": 3,
      "serve": 3,
      "connect": 3,
      "prune": 3,
      "light": 3,
      "clients": 3,
      "pre": 2,
      "license": 2,
      "bsd": 2,
      "clause": 2,
      "allow": 2,
      "limited": 2,
      "serving": 2,
      "connecting": 2,
      "outbound": 2,
      "new": 2,
      "signaled": 2,
      "288": 2,
      "address": 2,
      "following": 2,
      "addr": 2,
      "message": 2,
      "fingerprinting": 2,
      "bits": 2,
      "filtered": 2,
      "dns": 2,
      "pull": 2
    },
    "explicit_references": [],
    "explicit_dependencies": [],
    "implicit_dependencies": []
  }
}